{
    "description": "A fast and polyglot tool for code searching, linting, rewriting at large scale.",
    "version": "0.40.2",
    "homepage": "https://ast-grep.github.io",
    "license": "MIT",
    "architecture": {
        "64bit": {
            "url": "https://github.com/ast-grep/ast-grep/releases/download/0.40.2/app-x86_64-pc-windows-msvc.zip",
            "hash": "sha256:16c7ec442a3f2a44afce174879706bc4bf6be2f235db8463985997aafaeb3e2e"
        },
        "arm64": {
            "url": "https://github.com/ast-grep/ast-grep/releases/download/0.40.2/app-aarch64-pc-windows-msvc.zip",
            "hash": "sha256:8bf6498e091408e1bf5617e6a1cdef8e868ce1762316148cd9439de8835e24de"
        }
    },
    "extension": "zip",
    "links": [
        "sg.exe",
        "ast-grep.exe"
    ]
}
