{
    "description": "CMake is an open-source, cross-platform family of tools designed to build, test and package software",
    "version": "3.21.0",
    "url": "https://github.com/Kitware/CMake/releases/download/v3.21.0/cmake-3.21.0-windows-i386.zip",
    "url.hash": "SHA256:11ee86b7f9799724fc16664c63e308bfe3fbc22c9df8ef4955ad4b248f3e680b",
    "url64": "https://github.com/Kitware/CMake/releases/download/v3.21.0/cmake-3.21.0-windows-x86_64.zip",
    "url64.hash": "SHA256:c7b88c907a753f4ec86e43ddc89f91f70bf1b011859142f7f29e6d51ea4abb3c",
    "extension": "zip",
    "links": [
        "bin\\cmake.exe",
        "bin\\cmake-gui.exe",
        "bin\\cmcldeps.exe",
        "bin\\cpack.exe",
        "bin\\ctest.exe"
    ]
}
