{
    "description": "Curl is a command-line tool for transferring data specified with URL syntax.",
    "version": "8.14.1",
    "homepage": "https://curl.se/",
    "license": "https://github.com/curl/curl/blob/master/COPYING",
    "architecture": {
        "64bit": {
            "url": "https://curl.se/windows/dl-8.14.1_1/curl-8.14.1_1-win64-mingw.zip",
            "hash": "SHA256:eef8ed31fccd4ed22da9c5469c31cf1355096c41f9246f48ca1aa8086c6cb5d6"
        },
        "arm64": {
            "url": "https://curl.se/windows/dl-8.14.1_1/curl-8.14.1_1-win64a-mingw.zip",
            "hash": "SHA256:b9b33024e58348d76b8fd45c9ac11609d17cb6e6c9d3e0663d67c181b1b5721f"
        }
    },
    "extension": "zip",
    "links": [
        "bin/curl.exe",
        "bin/curl-ca-bundle.crt"
    ]
}
