{
    "description": "D is a general-purpose programming language with static typing, systems-level access, and C-like syntax",
    "version": "2.111.0",
    "homepage": "https://dlang.org/",
    "license": "BSL-1.0",
    "architecture": {
        "32bit": {
            "url": "https://downloads.dlang.org/releases/2.x/2.111.0/dmd.2.111.0.windows.7z",
            "hash": "SHA256:c26f7146718331e728716bda361ef7b65083ae853e36766294cc41661ab94010"
        }
    },
    "extension": "7z",
    "venv": {
        "category": "dlang",
        "path": [
            "${BAULK_PKGROOT}\\windows\\bin"
        ],
        "env": [
            "BAULK_DLANG_VERSION=2.110.0"
        ]
    }
}
