{
    "description": "GraalVM is a high-performance runtime that provides significant improvements in application performance and efficiency which is ideal for microservices",
    "version": "21.2.0",
    "homepage": "https://www.graalvm.org/",
    "license": "GPL",
    "url64": "https://github.com/graalvm/graalvm-ce-builds/releases/download/vm-21.2.0/graalvm-ce-java16-windows-amd64-21.2.0.zip",
    "url64.hash": "SHA256:dae2511abff8ead3ebc90cd9fc81a8e84b762fc91462b198c3eddf28f81a937e",
    "extension": "zip",
    "venv": {
        "category": "java",
        "path": "${BAULK_PKGROOT}\\bin",
        "env": [
            "JAVA_HOME=${BAULK_PKGROOT}",
            "GRAALVM_HOME=${BAULK_PKGROOT}"
        ]
    }
}
