{
    "description": "Kotlin/Native is an LLVM backend for the Kotlin compiler, runtime implementation, and native code generation facility using the LLVM toolchain.",
    "version": "1.9.0",
    "homepage": "https://github.com/JetBrains/kotlin",
    "license": "Apache-2.0",
    "url64": "https://github.com/JetBrains/kotlin/releases/download/v1.9.0/kotlin-native-windows-x86_64-1.9.0.zip",
    "url64.hash": "SHA256:989cb5cb28da87ad0ae2a9469dbbce227165014217ec472eeb78468045dcb766",
    "extension": "zip",
    "force_delete": [
        "${BAULK_VFS}\\.konan"
    ],
    "venv": {
        "category": "kotlin",
        "dependencies": [
            "zulu"
        ],
        "path": "${BAULK_PKGROOT}\\bin",
        "env": [
            "KONAN_DATA_DIR=${BAULK_VFS}\\.konan"
        ]
    }
}
