{
    "description": "LDC is LLVM based D-language compiler",
    "version": "1.35.0",
    "homepage": "https://github.com/ldc-developers/ldc",
    "license": "BSD-3-Clause",
    "url64": "https://github.com/ldc-developers/ldc/releases/download/v1.35.0/ldc2-1.35.0-windows-x64.7z",
    "url64.hash": "SHA256:ca8c6ea65943572689ccca2e891d4721d7f87153bea8651ff98cc169e519ac70",
    "extension": "7z",
    "venv": {
        "category": "dlang",
        "path": "${BAULK_PKGROOT}\\bin",
        "env": [
            "BAULK_LDC_VERSION=1.28.0"
        ]
    }
}
