{
    "description": "Feature-rich terminal-based text viewer",
    "version": "0.54.0",
    "homepage": "https://noborus.github.io/ov",
    "license": "MIT",
    "architecture": {
        "64bit": {
            "url": "https://github.com/noborus/ov/releases/download/v0.54.0/ov_0.54.0_windows_amd64.zip",
            "hash": "sha256:877297f8746807cfd29ab970764a25ea15971544faa0db004d223d3984ef2da5"
        },
        "arm64": {
            "url": "https://github.com/noborus/ov/releases/download/v0.54.0/ov_0.54.0_windows_arm64.zip",
            "hash": "sha256:77b8d719ebc28bd4ca5b2203c9168bad238cfc84855e0b3ce00110927c09ab9d"
        }
    },
    "extension": "zip",
    "links": [
        "ov.exe"
    ]
}
