{
    "description": "Execute commands in response to file modifications.",
    "version": "2.5.0",
    "homepage": "https://github.com/watchexec/watchexec",
    "license": "Apache-2.0",
    "architecture": {
        "64bit": {
            "url": "https://github.com/watchexec/watchexec/releases/download/v2.5.0/watchexec-2.5.0-x86_64-pc-windows-msvc.zip",
            "hash": "sha256:ecfc8457d30f0ebe5fdc6f67fed87e9114eee551310ebb66449629a5994f843c"
        }
    },
    "extension": "zip",
    "links": [
        "watchexec.exe"
    ]
}
