{
    "description": "Curl is a command-line tool for transferring data specified with URL syntax. (msvc flavor)",
    "version": "7.87.0.1",
    "homepage": "https://github.com/fcharlie/wincurl/",
    "license": "MIT",
    "url64": "https://github.com/fcharlie/wincurl/releases/download/7.87.0.1/wincurl-win64-7.87.0.1.zip",
    "url64.hash": "SHA256:525edf071d6e803dd0f6684edafb49ea49914f149cdb0e6162aceb1c67250b31",
    "urlarm64": "https://github.com/fcharlie/wincurl/releases/download/7.87.0.1/wincurl-arm64-7.87.0.1.zip",
    "urlarm64.hash": "SHA256:9d1b92e2bcd525ff7d3059bf583656c491a30afee50d1a677430502d168ccfff",
    "extension": "zip",
    "launchers": [
        "bin/curl.exe@wincurl.exe"
    ]
}
